proggy/__init__.py
proggy/error.py
proggy/progress.py
proggy/py.typed
proggy/tty/__init__.py
proggy/tty/ansi.py
proggy/tty/console.py
proggy/tty/drawing_mixin.py
proggy/tty/error.py
proggy/tty/position.py
proggy/tty/tty_drawable.py
proggy/tty/tty_multi_progress_bar.py
proggy/tty/tty_progress_bar.py
proggy/types.py
proggy/util.py
proggy-0.4.3.dist-info/LICENSE.md
proggy-0.4.3.dist-info/WHEEL
proggy-0.4.3.dist-info/METADATA
proggy-0.4.3.dist-info/RECORD
