Metadata-Version: 2.1
Name: proggy
Version: 0.4.3
Summary: A progress bar generator.
License: MIT
Author: Tarcísio Eduardo Moreira Crocomo
Author-email: tarcisioe@pm.me
Requires-Python: >=3.7,<4.0
Classifier: License :: OSI Approved :: MIT License
Classifier: Programming Language :: Python :: 3
Classifier: Programming Language :: Python :: 3.7
Classifier: Programming Language :: Python :: 3.8
Requires-Dist: typing_extensions (>=3.7.4,<4.0.0)
